testconfig.py
nose_testconfig-0.10.dist-info/DESCRIPTION.rst
nose_testconfig-0.10.dist-info/METADATA
nose_testconfig-0.10.dist-info/RECORD
nose_testconfig-0.10.dist-info/WHEEL
nose_testconfig-0.10.dist-info/entry_points.txt
nose_testconfig-0.10.dist-info/metadata.json
nose_testconfig-0.10.dist-info/top_level.txt
